<?xml version="1.0" encoding="utf-8" ?>
<dwsync>
<file name="3024-day.css" server="headkino.de//headkino/alldata/" local="130611203960000000" remote="130682336400000000" Dst="1" />
<file name="3024-night.css" server="headkino.de//headkino/alldata/" local="130611203960000000" remote="130682336400000000" Dst="1" />
<file name="ambiance-mobile.css" server="headkino.de//headkino/alldata/" local="130611203960000000" remote="130682336400000000" Dst="1" />
<file name="ambiance.css" server="headkino.de//headkino/alldata/" local="130611203960000000" remote="130682336400000000" Dst="1" />
<file name="base16-dark.css" server="headkino.de//headkino/alldata/" local="130611203960000000" remote="130682336400000000" Dst="1" />
<file name="base16-light.css" server="headkino.de//headkino/alldata/" local="130611203960000000" remote="130682336400000000" Dst="1" />
<file name="blackboard.css" server="headkino.de//headkino/alldata/" local="130611203960000000" remote="130682336400000000" Dst="1" />
<file name="cobalt.css" server="headkino.de//headkino/alldata/" local="130611203960000000" remote="130682336400000000" Dst="1" />
<file name="eclipse.css" server="headkino.de//headkino/alldata/" local="130611203960000000" remote="130682336400000000" Dst="1" />
<file name="elegant.css" server="headkino.de//headkino/alldata/" local="130611203960000000" remote="130682336400000000" Dst="1" />
<file name="lesser-dark.css" server="headkino.de//headkino/alldata/" local="130611203960000000" remote="130682336400000000" Dst="1" />
<file name="erlang-dark.css" server="headkino.de//headkino/alldata/" local="130611203960000000" remote="130682336400000000" Dst="1" />
<file name="mbo.css" server="headkino.de//headkino/alldata/" local="130611203960000000" remote="130682336400000000" Dst="1" />
<file name="mdn-like.css" server="headkino.de//headkino/alldata/" local="130611203960000000" remote="130682336400000000" Dst="1" />
<file name="midnight.css" server="headkino.de//headkino/alldata/" local="130611203960000000" remote="130682336400000000" Dst="1" />
<file name="monokai.css" server="headkino.de//headkino/alldata/" local="130611203960000000" remote="130682336400000000" Dst="1" />
<file name="neat.css" server="headkino.de//headkino/alldata/" local="130611203960000000" remote="130682336400000000" Dst="1" />
<file name="neo.css" server="headkino.de//headkino/alldata/" local="130611203960000000" remote="130682336400000000" Dst="1" />
<file name="night.css" server="headkino.de//headkino/alldata/" local="130611203960000000" remote="130682336400000000" Dst="1" />
<file name="paraiso-dark.css" server="headkino.de//headkino/alldata/" local="130611203960000000" remote="130682336400000000" Dst="1" />
<file name="paraiso-light.css" server="headkino.de//headkino/alldata/" local="130611203960000000" remote="130682336400000000" Dst="1" />
<file name="pastel-on-dark.css" server="headkino.de//headkino/alldata/" local="130611203960000000" remote="130682336400000000" Dst="1" />
<file name="rubyblue.css" server="headkino.de//headkino/alldata/" local="130611203960000000" remote="130682336400000000" Dst="1" />
<file name="solarized.css" server="headkino.de//headkino/alldata/" local="130611203960000000" remote="130682336400000000" Dst="1" />
<file name="the-matrix.css" server="headkino.de//headkino/alldata/" local="130611203960000000" remote="130682336400000000" Dst="1" />
<file name="tomorrow-night-eighties.css" server="headkino.de//headkino/alldata/" local="130611203960000000" remote="130682336400000000" Dst="1" />
<file name="twilight.css" server="headkino.de//headkino/alldata/" local="130611203960000000" remote="130682336400000000" Dst="1" />
<file name="vibrant-ink.css" server="headkino.de//headkino/alldata/" local="130611203960000000" remote="130682336400000000" Dst="1" />
<file name="xq-dark.css" server="headkino.de//headkino/alldata/" local="130611203960000000" remote="130682336400000000" Dst="1" />
<file name="xq-light.css" server="headkino.de//headkino/alldata/" local="130611203960000000" remote="130682336400000000" Dst="1" />
</dwsync>